{"data":{"id":"179","type":"pokemon","attributes":{"name":{"english":"Mareep","japanese":"メリープ","chinese":"咩利羊","french":"Wattouat"},"type":["Electric"],"base":{"HP":55,"Attack":40,"Defense":40,"Sp. Attack":65,"Sp. Defense":45,"Speed":35},"species":"Wool Pokémon","description":"Rubbing its fleece generates electricity. You’ll want to pet it because it’s cute, but if you use your bare hand, you’ll get a painful shock.","evolution":{"next":[["180","Level 15"]]},"profile":{"height":"0.6 m","weight":"7.8 kg","egg":["Monster","Field"],"ability":[["Static","false"],["Plus","true"]],"gender":"50:50"},"image":{"sprite":"https://raw.githubusercontent.com/IgnaceMaes/pokemon-data.json/master/images/pokedex/sprites/179.png","thumbnail":"https://raw.githubusercontent.com/IgnaceMaes/pokemon-data.json/master/images/pokedex/thumbnails/179.png","hires":"https://raw.githubusercontent.com/IgnaceMaes/pokemon-data.json/master/images/pokedex/hires/179.png"}}}}