{"data":{"id":"235","type":"pokemon","attributes":{"name":{"english":"Smeargle","japanese":"ドーブル","chinese":"图图犬","french":"Queulorior"},"type":["Normal"],"base":{"HP":55,"Attack":20,"Defense":35,"Sp. Attack":20,"Sp. Defense":45,"Speed":75},"species":"Painter Pokémon","description":"It draws symbols with the fluid that oozes from the tip of its tail. Depending on the symbol, Smeargle fanatics will pay big money for them.","evolution":{},"profile":{"height":"1.2 m","weight":"58 kg","egg":["Field"],"ability":[["Own Tempo","false"],["Technician","false"],["Moody","true"]],"gender":"50:50"},"image":{"sprite":"https://raw.githubusercontent.com/IgnaceMaes/pokemon-data.json/master/images/pokedex/sprites/235.png","thumbnail":"https://raw.githubusercontent.com/IgnaceMaes/pokemon-data.json/master/images/pokedex/thumbnails/235.png","hires":"https://raw.githubusercontent.com/IgnaceMaes/pokemon-data.json/master/images/pokedex/hires/235.png"}}}}