{"data":{"id":"277","type":"pokemon","attributes":{"name":{"english":"Swellow","japanese":"オオスバメ","chinese":"大王燕","french":"Hélédelle"},"type":["Normal","Flying"],"base":{"HP":60,"Attack":85,"Defense":60,"Sp. Attack":75,"Sp. Defense":50,"Speed":125},"species":"Swallow Pokémon","description":"Swellow is very conscientious about the upkeep of its glossy wings. Once two Swellow are gathered, they diligently take care of cleaning each other’s wings.","evolution":{"prev":["276","Level 22"]},"profile":{"height":"0.7 m","weight":"19.8 kg","egg":["Flying"],"ability":[["Guts","false"],["Scrappy","true"]],"gender":"50:50"},"image":{"sprite":"https://raw.githubusercontent.com/IgnaceMaes/pokemon-data.json/master/images/pokedex/sprites/277.png","thumbnail":"https://raw.githubusercontent.com/IgnaceMaes/pokemon-data.json/master/images/pokedex/thumbnails/277.png","hires":"https://raw.githubusercontent.com/IgnaceMaes/pokemon-data.json/master/images/pokedex/hires/277.png"}}}}