{"data":{"id":"382","type":"pokemon","attributes":{"name":{"english":"Kyogre","japanese":"カイオーガ","chinese":"盖欧卡","french":"Kyogre"},"type":["Water"],"base":{"HP":100,"Attack":100,"Defense":90,"Sp. Attack":150,"Sp. Defense":140,"Speed":90},"species":"Sea Basin Pokémon","description":"Kyogre is said to be the personification of the sea itself. Legends tell of its many clashes against Groudon, as each sought to gain the power of nature.","evolution":{},"profile":{"height":"4.5 m","weight":"352 kg","egg":["Undiscovered"],"ability":[["Drizzle","false"]],"gender":"Genderless"},"image":{"sprite":"https://raw.githubusercontent.com/IgnaceMaes/pokemon-data.json/master/images/pokedex/sprites/382.png","thumbnail":"https://raw.githubusercontent.com/IgnaceMaes/pokemon-data.json/master/images/pokedex/thumbnails/382.png","hires":"https://raw.githubusercontent.com/IgnaceMaes/pokemon-data.json/master/images/pokedex/hires/382.png"}}}}