{"data":{"id":"441","type":"pokemon","attributes":{"name":{"english":"Chatot","japanese":"ペラップ","chinese":"聒噪鸟","french":"Pijako"},"type":["Normal","Flying"],"base":{"HP":76,"Attack":65,"Defense":45,"Sp. Attack":92,"Sp. Defense":42,"Speed":91},"species":"Music Note Pokémon","description":"It can learn and speak human words. If they gather, they all learn the same saying.","evolution":{},"profile":{"height":"0.5 m","weight":"1.9 kg","egg":["Flying"],"ability":[["Keen Eye","false"],["Tangled Feet","false"],["Big Pecks","true"]],"gender":"50:50"},"image":{"sprite":"https://raw.githubusercontent.com/IgnaceMaes/pokemon-data.json/master/images/pokedex/sprites/441.png","thumbnail":"https://raw.githubusercontent.com/IgnaceMaes/pokemon-data.json/master/images/pokedex/thumbnails/441.png","hires":"https://raw.githubusercontent.com/IgnaceMaes/pokemon-data.json/master/images/pokedex/hires/441.png"}}}}