{"data":{"id":"508","type":"pokemon","attributes":{"name":{"english":"Stoutland","japanese":"ムーランド","chinese":"长毛狗","french":"Mastouffe"},"type":["Normal"],"base":{"HP":85,"Attack":110,"Defense":90,"Sp. Attack":45,"Sp. Defense":90,"Speed":80},"species":"Big-Hearted Pokémon","description":"Its fur is long and thick. A long time ago in cold regions, every household kept a Stoutland.","evolution":{"prev":["507","Level 32"]},"profile":{"height":"1.2 m","weight":"61 kg","egg":["Field"],"ability":[["Intimidate","false"],["Sand Rush","false"],["Scrappy","true"]],"gender":"50:50"},"image":{"sprite":"https://raw.githubusercontent.com/IgnaceMaes/pokemon-data.json/master/images/pokedex/sprites/508.png","thumbnail":"https://raw.githubusercontent.com/IgnaceMaes/pokemon-data.json/master/images/pokedex/thumbnails/508.png","hires":"https://raw.githubusercontent.com/IgnaceMaes/pokemon-data.json/master/images/pokedex/hires/508.png"}}}}