{"data":{"id":"54","type":"pokemon","attributes":{"name":{"english":"Psyduck","japanese":"コダック","chinese":"可达鸭","french":"Psykokwak"},"type":["Water"],"base":{"HP":50,"Attack":52,"Defense":48,"Sp. Attack":65,"Sp. Defense":50,"Speed":55},"species":"Duck Pokémon","description":"It has been found that its brain cells are 10 times more active when Psyduck is experiencing a headache.","evolution":{"next":[["55","Level 33"]]},"profile":{"height":"0.8 m","weight":"19.6 kg","egg":["Water 1","Field"],"ability":[["Damp","false"],["Cloud Nine","false"],["Swift Swim","true"]],"gender":"50:50"},"image":{"sprite":"https://raw.githubusercontent.com/IgnaceMaes/pokemon-data.json/master/images/pokedex/sprites/054.png","thumbnail":"https://raw.githubusercontent.com/IgnaceMaes/pokemon-data.json/master/images/pokedex/thumbnails/054.png","hires":"https://raw.githubusercontent.com/IgnaceMaes/pokemon-data.json/master/images/pokedex/hires/054.png"}}}}