{"data":{"id":"549","type":"pokemon","attributes":{"name":{"english":"Lilligant","japanese":"ドレディア","chinese":"裙儿小姐","french":"Fragilady"},"type":["Grass"],"base":{"HP":70,"Attack":60,"Defense":75,"Sp. Attack":110,"Sp. Defense":75,"Speed":90},"species":"Flowering Pokémon","description":"It’s well liked by other Pokémon because of its beauty. The flower on its head needs constant care, or it will soon wither and rot.","evolution":{"prev":["548","use Sun Stone"]},"profile":{"height":"1.1 m","weight":"16.3 kg","egg":["Grass"],"ability":[["Chlorophyll","false"],["Own Tempo","false"],["Leaf Guard","true"]],"gender":"0:100"},"image":{"sprite":"https://raw.githubusercontent.com/IgnaceMaes/pokemon-data.json/master/images/pokedex/sprites/549.png","thumbnail":"https://raw.githubusercontent.com/IgnaceMaes/pokemon-data.json/master/images/pokedex/thumbnails/549.png","hires":"https://raw.githubusercontent.com/IgnaceMaes/pokemon-data.json/master/images/pokedex/hires/549.png"}}}}