{"data":{"id":"568","type":"pokemon","attributes":{"name":{"english":"Trubbish","japanese":"ヤブクロン","chinese":"破破袋","french":"Miamiasme"},"type":["Poison"],"base":{"HP":50,"Attack":50,"Defense":62,"Sp. Attack":40,"Sp. Defense":62,"Speed":65},"species":"Trash Bag Pokémon","description":"If a young Pokémon or child breathes in the toxic gas that Trubbish belches out, it could be a life-threatening situation.","evolution":{"next":[["569","Level 36"]]},"profile":{"height":"0.6 m","weight":"31 kg","egg":["Mineral"],"ability":[["Stench","false"],["Sticky Hold","false"],["Aftermath","true"]],"gender":"50:50"},"image":{"sprite":"https://raw.githubusercontent.com/IgnaceMaes/pokemon-data.json/master/images/pokedex/sprites/568.png","thumbnail":"https://raw.githubusercontent.com/IgnaceMaes/pokemon-data.json/master/images/pokedex/thumbnails/568.png","hires":"https://raw.githubusercontent.com/IgnaceMaes/pokemon-data.json/master/images/pokedex/hires/568.png"}}}}