{"data":{"id":"588","type":"pokemon","attributes":{"name":{"english":"Karrablast","japanese":"カブルモ","chinese":"盖盖虫","french":"Carabing"},"type":["Bug"],"base":{"HP":50,"Attack":75,"Defense":45,"Sp. Attack":40,"Sp. Defense":45,"Speed":60},"species":"Clamping Pokémon","description":"For some reason they evolve when they receive electrical energy while they are attacking Shelmet.","evolution":{"next":[["589","Trade with Shelmet"]]},"profile":{"height":"0.5 m","weight":"5.9 kg","egg":["Bug"],"ability":[["Swarm","false"],["Shed Skin","false"],["No Guard","true"]],"gender":"50:50"},"image":{"sprite":"https://raw.githubusercontent.com/IgnaceMaes/pokemon-data.json/master/images/pokedex/sprites/588.png","thumbnail":"https://raw.githubusercontent.com/IgnaceMaes/pokemon-data.json/master/images/pokedex/thumbnails/588.png","hires":"https://raw.githubusercontent.com/IgnaceMaes/pokemon-data.json/master/images/pokedex/hires/588.png"}}}}