{"data":{"id":"69","type":"pokemon","attributes":{"name":{"english":"Bellsprout","japanese":"マダツボミ","chinese":"喇叭芽","french":"Chétiflor"},"type":["Grass","Poison"],"base":{"HP":50,"Attack":75,"Defense":35,"Sp. Attack":70,"Sp. Defense":30,"Speed":40},"species":"Flower Pokémon","description":"Bellsprout’s thin and flexible body lets it bend and sway to avoid any attack, however strong it may be. From its mouth, this Pokémon spits a corrosive fluid that melts even iron.","evolution":{"next":[["70","Level 21"]]},"profile":{"height":"0.7 m","weight":"4 kg","egg":["Grass"],"ability":[["Chlorophyll","false"],["Gluttony","true"]],"gender":"50:50"},"image":{"sprite":"https://raw.githubusercontent.com/IgnaceMaes/pokemon-data.json/master/images/pokedex/sprites/069.png","thumbnail":"https://raw.githubusercontent.com/IgnaceMaes/pokemon-data.json/master/images/pokedex/thumbnails/069.png","hires":"https://raw.githubusercontent.com/IgnaceMaes/pokemon-data.json/master/images/pokedex/hires/069.png"}}}}