{"data":{"id":"732","type":"pokemon","attributes":{"name":{"english":"Trumbeak","japanese":"ケララッパ","chinese":"喇叭啄鸟","french":"Piclairon"},"type":["Normal","Flying"],"base":{"HP":55,"Attack":85,"Defense":50,"Sp. Attack":40,"Sp. Defense":50,"Speed":75},"species":"Bugle Beak Pokémon","description":"From its mouth, it fires the seeds of berries it has eaten. The scattered seeds give rise to new plants.","evolution":{"prev":["731","Level 14"],"next":[["733","Level 28"]]},"profile":{"height":"0.6 m","weight":"14.8 kg","egg":["Flying"],"ability":[["Keen Eye","false"],["Skill Link","false"],["Pickup","true"]],"gender":"50:50"},"image":{"sprite":"https://raw.githubusercontent.com/IgnaceMaes/pokemon-data.json/master/images/pokedex/sprites/732.png","thumbnail":"https://raw.githubusercontent.com/IgnaceMaes/pokemon-data.json/master/images/pokedex/thumbnails/732.png","hires":"https://raw.githubusercontent.com/IgnaceMaes/pokemon-data.json/master/images/pokedex/hires/732.png"}}}}