{"data":{"id":"97","type":"pokemon","attributes":{"name":{"english":"Hypno","japanese":"スリーパー","chinese":"引梦貘人","french":"Hypnomade"},"type":["Psychic"],"base":{"HP":85,"Attack":73,"Defense":70,"Sp. Attack":73,"Sp. Defense":115,"Speed":67},"species":"Hypnosis Pokémon","description":"There are some Hypno that assist doctors with patients who can’t sleep at night in hospitals.","evolution":{"prev":["96","Level 26"]},"profile":{"height":"1.6 m","weight":"75.6 kg","egg":["Human-Like"],"ability":[["Insomnia","false"],["Forewarn","false"],["Inner Focus","true"]],"gender":"50:50"},"image":{"sprite":"https://raw.githubusercontent.com/IgnaceMaes/pokemon-data.json/master/images/pokedex/sprites/097.png","thumbnail":"https://raw.githubusercontent.com/IgnaceMaes/pokemon-data.json/master/images/pokedex/thumbnails/097.png","hires":"https://raw.githubusercontent.com/IgnaceMaes/pokemon-data.json/master/images/pokedex/hires/097.png"}}}}